zeusapi.py
zeusapi-0.1.1.dist-info/LICENSE
zeusapi-0.1.1.dist-info/WHEEL
zeusapi-0.1.1.dist-info/METADATA
zeusapi-0.1.1.dist-info/RECORD
