Metadata-Version: 2.1
Name: zeusapi
Version: 0.1.1
Summary: zeusapi.py
Author-email: "Matthew J. Lewis" <lightscalar@protonmail.com>
Classifier: License :: OSI Approved :: MIT License
Project-URL: Home, https://app.zeusapi.io
